xmarte/__init__.py
xmarte/__main__.py
xmarte/qt.py
xmarte/nodeeditor/node_edge.py
xmarte/nodeeditor/node_edge_dragging.py
xmarte/nodeeditor/node_edge_validators.py
xmarte/nodeeditor/node_editor_widget.py
xmarte/nodeeditor/node_graphics_edge.py
xmarte/nodeeditor/node_graphics_edge_path.py
xmarte/nodeeditor/node_graphics_node.py
xmarte/nodeeditor/node_graphics_scene.py
xmarte/nodeeditor/node_graphics_socket.py
xmarte/nodeeditor/node_graphics_view.py
xmarte/nodeeditor/node_node.py
xmarte/nodeeditor/node_scene.py
xmarte/nodeeditor/node_socket.py
xmarte/qt5/__init__.py
xmarte/qt5/exception_hook.py
xmarte/qt5/styles.css
xmarte/qt5/icons/__init__.py
xmarte/qt5/icons/back_to_start.png
xmarte/qt5/icons/delete.png
xmarte/qt5/icons/step_back.png
xmarte/qt5/libraries/__init__.py
xmarte/qt5/libraries/functions.py
xmarte/qt5/nodes/__init__.py
xmarte/qt5/nodes/marte2_base.py
xmarte/qt5/nodes/marte2_node.py
xmarte/qt5/nodes/node_factory.py
xmarte/qt5/nodes/node_graphics.py
xmarte/qt5/nodes/node_handler.py
xmarte/qt5/nodes/nodes.json
xmarte/qt5/plugins/__init__.py
xmarte/qt5/plugins/base_plugin.py
xmarte/qt5/plugins/marte2/marte2.py
xmarte/qt5/plugins/marte2/file_handlers/__init__.py
xmarte/qt5/plugins/marte2/file_handlers/cfg.py
xmarte/qt5/plugins/marte2/file_handlers/json.py
xmarte/qt5/plugins/marte2/file_handlers/python.py
xmarte/qt5/plugins/marte2/services/__init__.py
xmarte/qt5/plugins/widgets/__init__.py
xmarte/qt5/plugins/widgets/hover_button.py
xmarte/qt5/services/__init__.py
xmarte/qt5/services/config_manager.py
xmarte/qt5/services/recovery.py
xmarte/qt5/services/service.py
xmarte/qt5/services/split_view.py
xmarte/qt5/services/api_manager/__init__.py
xmarte/qt5/services/api_manager/api_manager.py
xmarte/qt5/services/api_manager/widgets/__init__.py
xmarte/qt5/services/api_manager/widgets/error_widget.py
xmarte/qt5/services/api_manager/windows/__init__.py
xmarte/qt5/services/api_manager/windows/error_check_wnd.py
xmarte/qt5/services/app_def/__init__.py
xmarte-1.0.0.dist-info/licenses/LICENSE
xmarte-1.0.0.dist-info/METADATA
xmarte-1.0.0.dist-info/WHEEL
xmarte-1.0.0.dist-info/top_level.txt
xmarte-1.0.0.dist-info/RECORD
