Metadata-Version: 2.4
Name: xmarte
Version: 1.0.0
Summary: A GUI Application for configuration MARTe2 applications.
Author-email: Edward Jones <edward.jones1@ukaea.uk>
Project-URL: Homepage, https://github.com/ukaea/xMARTe
Requires-Python: >=3.9
License-File: LICENSE
Requires-Dist: PyQt5>=5.15.2
Requires-Dist: PyQt5-Qt5>=5.15.2
Requires-Dist: qdarkgraystyle>=1.0.2
Requires-Dist: pandas>=2.0.2
Requires-Dist: qtpy>=2.4.1
Requires-Dist: pyyaml>=6.0.1
Requires-Dist: pytest>=8.1.1
Requires-Dist: pytest-qt>=4.4.0
Requires-Dist: ruff>=0.3.5
Requires-Dist: fpdf>=1.7.2
Requires-Dist: pyqtchart>=5.15.2
Requires-Dist: pyqt-modern-slider>=0.0.5
Requires-Dist: matplotlib>=3.8.3
Requires-Dist: cryptography>=42.0.8
Requires-Dist: pytest-mock>=3.14.0
Requires-Dist: scipy>=1.13.1
Requires-Dist: nodeeditor
Requires-Dist: martepy
Dynamic: license-file
